{
  "kind": "collectionType",
  "collectionName": "kyc_ses",
  "info": {
    "singularName": "kyc-se",
    "pluralName": "kyc-ses",
    "displayName": "KYC-SE",
    "description": ""
  },
  "options": {
    "draftAndPublish": false
  },
  "attributes": {
    "formName": {
      "type": "string",
      "required": true,
      "unique": false
    },
    "formHeader": {
      "type": "component",
      "repeatable": false,
      "component": "kyc.form-header"
    },
    "product": {
      "type": "relation",
      "relation": "manyToOne",
      "target": "api::product.product",
      "inversedBy": "kyc_ses"
    },
    "formType": {
      "pluginOptions": {},
      "type": "enumeration",
      "enum": [
        "onboarding",
        "update"
      ],
      "required": true
    },
    "setOfQuestions": {
      "pluginOptions": {},
      "type": "dynamiczone",
      "components": [
        "kyc.question"
      ],
      "required": true
    }
  }
}
